precision_tree/__init__.py
precision_tree/enums.py
precision_tree/nodes.py
precision_tree/tree.py
precision_tree-0.1.3.dist-info/LICENSE
precision_tree-0.1.3.dist-info/METADATA
precision_tree-0.1.3.dist-info/WHEEL
precision_tree-0.1.3.dist-info/top_level.txt
precision_tree-0.1.3.dist-info/RECORD
