Metadata-Version: 2.1
Name: precision-tree
Version: 0.1.3
Summary: Precision Tree Module for precision decision analysis, supporting custom nodes (Decision, Chance, and Payoff) with visualization and optimal path calculation.
Home-page: https://github.com/danylevych/precision-tree
Author: Oleh Danylevych
Author-email: danylevych123@gmail.com
Classifier: Programming Language :: Python :: 3
Classifier: License :: OSI Approved :: MIT License
Classifier: Operating System :: OS Independent
Requires-Python: >=3.6
License-File: LICENSE
Requires-Dist: graphviz==0.20.3
Requires-Dist: setuptools==75.6.0
